tj.py
tj-2.8.14.dist-info/LICENSE.md
tj-2.8.14.dist-info/METADATA
tj-2.8.14.dist-info/WHEEL
tj-2.8.14.dist-info/top_level.txt
tj-2.8.14.dist-info/RECORD
